odoo8_addon_partner_contact_department-8.0.1.0.0.99.dev14-py2.7-nspkg.pth
odoo8_addon_partner_contact_department-8.0.1.0.0.99.dev14.dist-info/DESCRIPTION.rst
odoo8_addon_partner_contact_department-8.0.1.0.0.99.dev14.dist-info/METADATA
odoo8_addon_partner_contact_department-8.0.1.0.0.99.dev14.dist-info/RECORD
odoo8_addon_partner_contact_department-8.0.1.0.0.99.dev14.dist-info/WHEEL
odoo8_addon_partner_contact_department-8.0.1.0.0.99.dev14.dist-info/metadata.json
odoo8_addon_partner_contact_department-8.0.1.0.0.99.dev14.dist-info/namespace_packages.txt
odoo8_addon_partner_contact_department-8.0.1.0.0.99.dev14.dist-info/top_level.txt
odoo_addons/partner_contact_department/README.rst
odoo_addons/partner_contact_department/__init__.py
odoo_addons/partner_contact_department/__openerp__.py
odoo_addons/partner_contact_department/i18n/de.po
odoo_addons/partner_contact_department/i18n/es.po
odoo_addons/partner_contact_department/i18n/eu.po
odoo_addons/partner_contact_department/i18n/fi.po
odoo_addons/partner_contact_department/i18n/it.po
odoo_addons/partner_contact_department/i18n/partner_contact_department.pot
odoo_addons/partner_contact_department/i18n/sl.po
odoo_addons/partner_contact_department/models/__init__.py
odoo_addons/partner_contact_department/models/res_partner.py
odoo_addons/partner_contact_department/security/ir.model.access.csv
odoo_addons/partner_contact_department/static/description/icon.png
odoo_addons/partner_contact_department/views/res_partner_department_view.xml
odoo_addons/partner_contact_department/views/res_partner_view.xml
